Metadata-Version: 2.4
Name: psr-pycloud
Version: 0.3.9
Summary: PSRCloud Python Module
Author-email: Lucas Storino <lstorino@psr-inc.com>, Pedro Henrique <pedrohenrique@psr-inc.com>
Requires-Dist: zeep
Requires-Dist: filelock
Requires-Dist: pefile
